mongostick/__init__.py
mongostick/app.py
mongostick/settings.py
mongostick/frontend/build/asset-manifest.json
mongostick/frontend/build/favicon.ico
mongostick/frontend/build/index.html
mongostick/frontend/build/manifest.json
mongostick/frontend/build/service-worker.js
mongostick/frontend/build/static/css/main.0070a445.css
mongostick/frontend/build/static/js/main.456327fa.js
mongostick/handlers/__init__.py
mongostick/handlers/base_websocket.py
mongostick/handlers/main.py
mongostick/lib/__init__.py
mongostick/lib/mongo_scheduler.py
mongostick/lib/mongodb_encoder.py
mongostick-0.2.dist-info/DESCRIPTION.rst
mongostick-0.2.dist-info/METADATA
mongostick-0.2.dist-info/RECORD
mongostick-0.2.dist-info/WHEEL
mongostick-0.2.dist-info/entry_points.txt
mongostick-0.2.dist-info/metadata.json
mongostick-0.2.dist-info/top_level.txt
mongostick-0.2.dist-info/zip-safe
