Metadata-Version: 2.0
Name: mongostick
Version: 0.2
Summary: MongoStick helps you to poke around your database.
Home-page: https://github.com/RockingRolli/mongostick
Author: Roland von Ohlen
Author-email: webwork@rvo.name
License: MIT
Platform: UNKNOWN
Classifier: Development Status :: 3 - Alpha
Classifier: Programming Language :: Python
Requires-Dist: motor (==1.1)
Requires-Dist: tornado (==4.5.2)
Provides-Extra: develop
